README.txt
setup.cfg
setup.py
getpaid/__init__.py
getpaid.SalesforcePloneFormGenAdapter.egg-info/PKG-INFO
getpaid.SalesforcePloneFormGenAdapter.egg-info/SOURCES.txt
getpaid.SalesforcePloneFormGenAdapter.egg-info/dependency_links.txt
getpaid.SalesforcePloneFormGenAdapter.egg-info/entry_points.txt
getpaid.SalesforcePloneFormGenAdapter.egg-info/namespace_packages.txt
getpaid.SalesforcePloneFormGenAdapter.egg-info/not-zip-safe
getpaid.SalesforcePloneFormGenAdapter.egg-info/requires.txt
getpaid.SalesforcePloneFormGenAdapter.egg-info/top_level.txt
getpaid/SalesforcePloneFormGenAdapter/CHANGES.txt
getpaid/SalesforcePloneFormGenAdapter/LICENSE.GPL
getpaid/SalesforcePloneFormGenAdapter/LICENSE.txt
getpaid/SalesforcePloneFormGenAdapter/README.txt
getpaid/SalesforcePloneFormGenAdapter/TODO.txt
getpaid/SalesforcePloneFormGenAdapter/__init__.py
getpaid/SalesforcePloneFormGenAdapter/config.py
getpaid/SalesforcePloneFormGenAdapter/configure.zcml
getpaid/SalesforcePloneFormGenAdapter/messagefactory_.py
getpaid/SalesforcePloneFormGenAdapter/version.txt
getpaid/SalesforcePloneFormGenAdapter/Extensions/Install.py
getpaid/SalesforcePloneFormGenAdapter/Extensions/__init__.py
getpaid/SalesforcePloneFormGenAdapter/content/__init__.py
getpaid/SalesforcePloneFormGenAdapter/content/getpaidpfgsalesforceadapter.py
getpaid/SalesforcePloneFormGenAdapter/i18n/plone-salesforcepfgadapter.pot
getpaid/SalesforcePloneFormGenAdapter/migrations/__init__.py
getpaid/SalesforcePloneFormGenAdapter/profiles/default/factorytool.xml
getpaid/SalesforcePloneFormGenAdapter/profiles/default/skins.xml
getpaid/SalesforcePloneFormGenAdapter/profiles/default/types.xml
getpaid/SalesforcePloneFormGenAdapter/profiles/default/workflows.xml
getpaid/SalesforcePloneFormGenAdapter/profiles/default/types/GetPaidPFGSalesforceAdapter.xml
getpaid/SalesforcePloneFormGenAdapter/skins/salesforce-getpaid-adapter_images/salesforce.gif
getpaid/SalesforcePloneFormGenAdapter/tests/__init__.py
getpaid/SalesforcePloneFormGenAdapter/tests/base.py
getpaid/SalesforcePloneFormGenAdapter/tests/pfg_adapter_view.txt
getpaid/SalesforcePloneFormGenAdapter/tests/testGetPaidPFGSalesforceAdapterUninstall.py
getpaid/SalesforcePloneFormGenAdapter/tests/testSalesforce.py
getpaid/SalesforcePloneFormGenAdapter/tests/test_doctests.py