Metadata-Version: 1.0
Name: getpaid.SalesforcePloneFormGenAdapter
Version: 1.7
Summary: PloneFormGen adapter allowing for creation of arbitrary Salesforce.com         records based on data collected from a web form
Home-page: http://code.google.com/p/getpaid
Author: Rob LaRubbio
Author-email: rob@onenw.org
License: GPL
Keywords: Zope CMF Plone Salesforce.com CRM PloneFormGen forms integration
Platform: UNKNOWN
Classifier: Programming Language :: Python
Classifier: Topic :: Software Development :: Libraries :: Python Modules
Classifier: Framework :: Zope2
Classifier: Framework :: Plone
